{
  "action": {
    "description": "Committee Amendment \"A\" (S-309) READ and ADOPTED.",
    "occurred_at": "2025-06-09",
    "jurisdiction_id": "~{\"classification\": \"upper\"}",
    "session_id": "132",
    "entity_type": "bill",
    "classifications": [
      "committee-passage-favorable",
      "passage"
    ],
    "related_entities": [],
    "sources": [
      {
        "url": "https://legislature.maine.gov/LawMakerWeb/summary.asp?ID=280097243",
        "note": ""
      },
      {
        "url": "https://legislature.maine.gov/LawMakerWeb/sponsors.asp?ID=280097243",
        "note": ""
      },
      {
        "url": "https://legislature.maine.gov/LawMakerWeb/dockets.asp?ID=280097243",
        "note": ""
      },
      {
        "url": "https://legislature.maine.gov/LawMakerWeb/subjects.asp?ID=280097243",
        "note": ""
      }
    ]
  },
  "bill_id": "LD 984"
}