{
  "action": {
    "description": "PASSED TO BE ENGROSSED AS AMENDED by Committee Amendment \"A\" (S-195) and Senate Amendment \"A\" (S-301) in NON-CONCURRENCE.",
    "occurred_at": "2025-06-09",
    "jurisdiction_id": "~{\"classification\": \"upper\"}",
    "session_id": "132",
    "entity_type": "bill",
    "classifications": [
      "reading-3"
    ],
    "related_entities": [],
    "sources": [
      {
        "url": "https://legislature.maine.gov/LawMakerWeb/summary.asp?ID=280096608",
        "note": ""
      },
      {
        "url": "https://legislature.maine.gov/LawMakerWeb/sponsors.asp?ID=280096608",
        "note": ""
      },
      {
        "url": "https://legislature.maine.gov/LawMakerWeb/dockets.asp?ID=280096608",
        "note": ""
      },
      {
        "url": "https://legislature.maine.gov/LawMakerWeb/subjects.asp?ID=280096608",
        "note": ""
      }
    ]
  },
  "bill_id": "LD 598"
}