{
  "legislative_session": "132",
  "identifier": "LD 2062",
  "title": "An Act To Enhance The Safety Of Public Transit Bus Operators Through The Installation Of Vehicle Security Barriers",
  "from_organization": "~{\"classification\": \"upper\"}",
  "classification": [
    "bill"
  ],
  "subject": [
    "BUSES",
    "PUBLIC TRANSPORTATION",
    "SECURITY BARRIERS"
  ],
  "abstracts": [],
  "other_titles": [],
  "other_identifiers": [
    {
      "identifier": "ocd-bill-me-132-ld2062"
    }
  ],
  "actions": [
    {
      "description": "Received by the Secretary of the Senate on December 15, 2025 and REFERRED to the Committee on TRANSPORTATION pursuant to Joint Rule 308.2",
      "date": "2025-12-15",
      "organization_id": "~{\"classification\": \"upper\"}",
      "classification": [
        "receipt",
        "referral-committee"
      ],
      "related_entities": [],
      "_processing": {
        "log_file_created": "2026-07-13T06:06:13Z"
      }
    }
  ],
  "sponsorships": [
    {
      "name": "Teresa PIERCE",
      "classification": "primary",
      "entity_type": "person",
      "primary": true,
      "person_id": "~{\"chamber\": \"upper\", \"name\": \"Teresa PIERCE\"}",
      "organization_id": null
    }
  ],
  "related_bills": [],
  "versions": [
    {
      "note": "LD 2062 SP 849",
      "links": [
        {
          "url": "http://www.mainelegislature.org/legis/bills/getPDF.asp?paper=SP0849&item=1&snum=132",
          "media_type": "application/pdf"
        }
      ],
      "date": "",
      "classification": ""
    }
  ],
  "documents": [],
  "citations": [],
  "sources": [
    {
      "url": "https://legislature.maine.gov/LawMakerWeb/summary.asp?ID=280100959",
      "note": ""
    },
    {
      "url": "https://legislature.maine.gov/LawMakerWeb/sponsors.asp?ID=280100959",
      "note": ""
    },
    {
      "url": "https://legislature.maine.gov/LawMakerWeb/dockets.asp?ID=280100959",
      "note": ""
    },
    {
      "url": "https://legislature.maine.gov/LawMakerWeb/subjects.asp?ID=280100959",
      "note": ""
    }
  ],
  "extras": {
    "ld_number": "LD 2062"
  },
  "jurisdiction": {
    "id": "ocd-jurisdiction/country:us/state:me/government",
    "name": "Maine",
    "classification": "state",
    "division_id": "ocd-division/country:us/state:me"
  },
  "_processing": {
    "logs_latest_update": "2026-07-13T06:06:13Z"
  }
}